gdrive_downloader/__init__.py
gdrive_downloader/downloader.py
gdrive_downloader-0.1.0.dist-info/METADATA
gdrive_downloader-0.1.0.dist-info/WHEEL
gdrive_downloader-0.1.0.dist-info/entry_points.txt
gdrive_downloader-0.1.0.dist-info/top_level.txt
gdrive_downloader-0.1.0.dist-info/RECORD
