Metadata-Version: 2.2
Name: gdrive_downloader
Version: 0.1.0
Summary: A CLI tool to download files or folders from Google Drive.
Home-page: https://github.com/penguinwang96825/gdrive_downloader
Author: Yang Wang
Author-email: yangwang4work@gmail.com
Classifier: Programming Language :: Python :: 3
Classifier: Operating System :: OS Independent
Requires-Dist: gdown
Requires-Dist: rich
Dynamic: author
Dynamic: author-email
Dynamic: classifier
Dynamic: home-page
Dynamic: requires-dist
Dynamic: summary
